aissemble_notebook_exporter/__init__.py
aissemble_notebook_exporter/quick_exporter.py
aissemble_notebook_exporter-1.0.0.dev1719419214.dist-info/LICENSE.txt
aissemble_notebook_exporter-1.0.0.dev1719419214.dist-info/METADATA
aissemble_notebook_exporter-1.0.0.dev1719419214.dist-info/WHEEL
aissemble_notebook_exporter-1.0.0.dev1719419214.dist-info/RECORD
